[
  {
    "id": 1,
    "name": "Organizers of political repressions",
    "shortName": "Organizers of Repressions",
    "ruName": "Организаторы политических репрессий",
    "ruShortName": "Организаторы репрессий",
    "count": 850
  },
  {
    "id": 2,
    "name": "Propagandists",
    "shortName": "Propagandists",
    "ruName": "Пропагандисты",
    "ruShortName": "Пропагандисты",
    "count": 747
  },
  {
    "id": 3,
    "name": "Key Local Government Officials",
    "shortName": "Local Officials",
    "ruName": "Ключевые региональные чиновники",
    "ruShortName": "Региональные чиновники",
    "count": 739
  },
  {
    "id": 4,
    "name": "Individuals involved in corruption",
    "shortName": "Corrupt Officials",
    "ruName": "Коррупционеры",
    "ruShortName": "Коррупционеры",
    "count": 721
  },
  {
    "id": 5,
    "name": "Members of Parliament and Senate",
    "shortName": "Parliament and Senate",
    "ruName": "Депутаты и сенаторы",
    "ruShortName": "Депутаты и сенаторы",
    "count": 619
  },
  {
    "id": 6,
    "name": "Warmongers",
    "shortName": "Warmongers",
    "ruName": "Разжигатели войны",
    "ruShortName": "Разжигатели войны",
    "count": 555
  },
  {
    "id": 7,
    "name": "Senior Federal Officials",
    "shortName": "Federal Officials",
    "ruName": "Высшие федеральные чиновники",
    "ruShortName": "Федеральные чиновники",
    "count": 475
  },
  {
    "id": 8,
    "name": "Putin’s Public Supporters",
    "shortName": "Putin’s Supporters",
    "ruName": "Публичные сторонники Путина",
    "ruShortName": "Сторонники Путина",
    "count": 468
  },
  {
    "id": 9,
    "name": "Key ‘siloviki’ (security forces) figure",
    "shortName": "Siloviki",
    "ruName": "Ключевые силовики",
    "ruShortName": "Cиловики",
    "count": 459
  },
  {
    "id": 10,
    "name": "Top Management of State Owned Companies",
    "shortName": "Top Managers",
    "ruName": "Руководители госкомпаний",
    "ruShortName": "Руководители госкомпаний",
    "count": 431
  },
  {
    "id": 11,
    "name": "‘United Russia’ party Functionaries",
    "shortName": "United Russia",
    "ruName": "Функционеры «Единой России»",
    "ruShortName": "Единая Россия",
    "count": 312
  },
  {
    "id": 12,
    "name": "Sellout opinion leaders",
    "shortName": "Influencers",
    "ruName": "Продажные лидеры общественного мнения",
    "ruShortName": "Инфлюенсеры",
    "count": 183
  },
  {
    "id": 13,
    "name": "War Arrangers",
    "shortName": "War Arrangers",
    "ruName": "Организаторы войны",
    "ruShortName": "Организаторы войны",
    "count": 131
  },
  {
    "id": 14,
    "name": "Election fraud organizers",
    "shortName": "Election Fraud",
    "ruName": "Организаторы фальсификаций на выборах",
    "ruShortName": "Фальсификаторы выборов",
    "count": 100
  },
  {
    "id": 15,
    "name": "Region Heads",
    "shortName": "Region Heads",
    "ruName": "Главы регионов",
    "ruShortName": "Главы регионов",
    "count": 89
  },
  {
    "id": 16,
    "name": "State Bankers",
    "shortName": "Bankers",
    "ruName": "Государственные банкиры",
    "ruShortName": "Банкиры",
    "count": 51
  }
]